edv_dwh_connector/__init__.py
edv_dwh_connector/dwh.py
edv_dwh_connector/exceptions.py
edv_dwh_connector/pg_dwh.py
edv_dwh_connector/pi_web_api_client.py
edv_dwh_connector/sync_data.py
edv_dwh_connector/blend_proposal/__init__.py
edv_dwh_connector/blend_proposal/blend_material.py
edv_dwh_connector/blend_proposal/blend_proposal.py
edv_dwh_connector/blend_proposal/blend_sequence.py
edv_dwh_connector/blend_proposal/db/__init__.py
edv_dwh_connector/blend_proposal/db/pg_blend_material.py
edv_dwh_connector/blend_proposal/db/pg_blend_proposal.py
edv_dwh_connector/blend_proposal/db/pg_blend_sequence.py
edv_dwh_connector/blend_proposal/excel/__init__.py
edv_dwh_connector/blend_proposal/excel/blend_material_start_cell.py
edv_dwh_connector/blend_proposal/excel/blend_proposal_start_cell.py
edv_dwh_connector/blend_proposal/excel/blend_sequence_start_cell.py
edv_dwh_connector/blend_proposal/excel/excel_blend_material.py
edv_dwh_connector/blend_proposal/excel/excel_blend_proposal.py
edv_dwh_connector/blend_proposal/excel/excel_blend_sequence.py
edv_dwh_connector/blend_proposal/excel/sequence_total_row.py
edv_dwh_connector/blend_proposal/excel/start_cell.py
edv_dwh_connector/blend_proposal/sync/__init__.py
edv_dwh_connector/blend_proposal/sync/sync_blend_proposals.py
edv_dwh_connector/pi/__init__.py
edv_dwh_connector/pi/pi_measure.py
edv_dwh_connector/pi/pi_tag.py
edv_dwh_connector/pi/sync_pi_data.py
edv_dwh_connector/pi/writer.py
edv_dwh_connector/pi/cached/__init__.py
edv_dwh_connector/pi/cached/cached_pi_measure.py
edv_dwh_connector/pi/cached/cached_pi_tag.py
edv_dwh_connector/pi/csv/__init__.py
edv_dwh_connector/pi/csv/csv_pi_measure.py
edv_dwh_connector/pi/csv/csv_writer.py
edv_dwh_connector/pi/db/__init__.py
edv_dwh_connector/pi/db/pg_pi_measure.py
edv_dwh_connector/pi/db/pg_pi_tag.py
edv_dwh_connector/pi/rest/__init__.py
edv_dwh_connector/pi/rest/rest_sync_pi_measures.py
edv_dwh_connector/pi/rest/rest_sync_pi_tags.py
edv_dwh_connector/utils/__init__.py
edv_dwh_connector-0.14.1.dist-info/LICENSE.txt
edv_dwh_connector-0.14.1.dist-info/METADATA
edv_dwh_connector-0.14.1.dist-info/WHEEL
edv_dwh_connector-0.14.1.dist-info/top_level.txt
edv_dwh_connector-0.14.1.dist-info/RECORD
