Metadata-Version: 2.1
Name: edv-dwh-connector
Version: 0.14.1
Summary: This module helps to connect to our data warehouse
Home-page: https://github.com/endeavourmining/edv-dwh-connector
Author: Endeavour Mining
Author-email: github@endeavourmining.com
Classifier: Programming Language :: Python :: 3
Classifier: License :: OSI Approved :: Apache Software License
Classifier: Operating System :: OS Independent
Requires-Python: >=3.8
License-File: LICENSE.txt
